semantic_prompt_packager/__init__.py
semantic_prompt_packager/cli.py
semantic_prompt_packager/core.py
semantic_prompt_packager/embedding.py
semantic_prompt_packager/manifest.py
semantic_prompt_packager/schema.json
llm_prompt_semantic_diff-0.1.0.dist-info/METADATA
llm_prompt_semantic_diff-0.1.0.dist-info/WHEEL
llm_prompt_semantic_diff-0.1.0.dist-info/entry_points.txt
llm_prompt_semantic_diff-0.1.0.dist-info/licenses/LICENSE
llm_prompt_semantic_diff-0.1.0.dist-info/RECORD
