Metadata-Version: 2.4
Name: llm-prompt-semantic-diff
Version: 0.1.0
Summary: A CLI tool for managing and comparing LLM prompts using semantic diffing
Project-URL: Homepage, https://github.com/aatakansalar/llm-prompt-semantic-diff
Project-URL: Repository, https://github.com/aatakansalar/llm-prompt-semantic-diff
Project-URL: Issues, https://github.com/aatakansalar/llm-prompt-semantic-diff/issues
Project-URL: Changelog, https://github.com/aatakansalar/llm-prompt-semantic-diff/blob/main/CHANGELOG.md
Author: Ahmet Atakan Salar
License: MIT
License-File: LICENSE
Keywords: ai,diff,llm,prompt,semantic,versioning
Classifier: Development Status :: 4 - Beta
Classifier: Intended Audience :: Developers
Classifier: License :: OSI Approved :: MIT License
Classifier: Programming Language :: Python :: 3
Classifier: Programming Language :: Python :: 3.10
Classifier: Programming Language :: Python :: 3.11
Classifier: Programming Language :: Python :: 3.12
Classifier: Topic :: Software Development :: Libraries :: Python Modules
Classifier: Topic :: Text Processing :: Linguistic
Requires-Python: >=3.10
Requires-Dist: jsonschema>=4.0.0
Requires-Dist: numpy>=1.24.0
Requires-Dist: openai>=1.0.0
Requires-Dist: pydantic>=2.0.0
Requires-Dist: rich>=13.0.0
Requires-Dist: scipy>=1.10.0
Requires-Dist: sentence-transformers>=2.2.0
Requires-Dist: typer>=0.9.0
Provides-Extra: dev
Requires-Dist: black>=23.0.0; extra == 'dev'
Requires-Dist: mypy>=1.0.0; extra == 'dev'
Requires-Dist: pytest-cov>=4.0.0; extra == 'dev'
Requires-Dist: pytest>=7.0.0; extra == 'dev'
Requires-Dist: ruff>=0.1.0; extra == 'dev'
